pyredis/__init__.py
pyredis/wrapper.py
py_redis-1.1.1.dist-info/LICENSE
py_redis-1.1.1.dist-info/METADATA
py_redis-1.1.1.dist-info/WHEEL
py_redis-1.1.1.dist-info/top_level.txt
py_redis-1.1.1.dist-info/RECORD
