Metadata-Version: 2.1
Name: py-redis
Version: 1.1.1
Summary: A convenience wrapper for the official Python redis package
Home-page: https://github.com/pkeilbach/pyredis
Author: Pascal Keilbach
Author-email: dev@pk17.org
License: UNKNOWN
Platform: UNKNOWN
Classifier: Programming Language :: Python :: 3
Classifier: License :: OSI Approved :: MIT License
Classifier: Operating System :: OS Independent
Requires-Python: >=3.6
License-File: LICENSE
